eyelinkparser/__init__.py
eyelinkparser/_events.py
eyelinkparser/_eyelinkparser.py
eyelinkparser/_traceprocessor.py
eyelinkparser/visualize.py
eyetribeparser/__init__.py
eyetribeparser/_eyetribeparser.py
gazepointparser/__init__.py
gazepointparser/_gazepointparser.py
smiparser/__init__.py
smiparser/_smiparser.py
python_eyelinkparser-0.17.3.dist-info/METADATA
python_eyelinkparser-0.17.3.dist-info/WHEEL
python_eyelinkparser-0.17.3.dist-info/top_level.txt
python_eyelinkparser-0.17.3.dist-info/RECORD
