Metadata-Version: 2.1
Name: python-eyelinkparser
Version: 0.17.3
Summary: An extensible parser for EyeLink data files (EDF)
Home-page: https://github.com/smathot/python-eyelinkparser
Author: Sebastiaan Mathot
Author-email: s.mathot@cogsci.nl
License: GNU GPL Version 3
Classifier: Development Status :: 4 - Beta
Classifier: Intended Audience :: Science/Research
Classifier: Topic :: Scientific/Engineering
Classifier: License :: OSI Approved :: GNU General Public License v3 (GPLv3)
Classifier: Programming Language :: Python :: 2
Classifier: Programming Language :: Python :: 3
Requires-Dist: python-datamatrix
Requires-Dist: fastnumbers
